{
  "id": "00000000-0000-0000-0000-000000000002",
  "pictureName": "Hearts",
  "pictureDescription": "Generates a picture of various hearts.",
  "author": "Bruce Johnson",
  "imageWidth": 520,
  "imageHeight": 520,
  "curves": [
    {
      "num": 1,
      "name": "Heart 1",
      "description": "A heart shape with 3 dots",
      "dotLocations": [
        {"x": 90+83, "y": 80},
        {"x": 155+83, "y": 101},
        {"x": 90+83, "y": 194}
      ],
      "startAngle": 0,
      "endAngle": 0,
      "isClockwise": true
    },
    {
      "num": 2,
      "name": "Heart 2",
      "description": "Another heart shape with 3 dots",
      "dotLocations": [
        {"x": 90+83, "y": 80},
        {"x": 25+83, "y": 101},
        {"x": 90+83, "y": 194}
      ],
      "startAngle": 0,
      "endAngle": 0,
      "isClockwise": true
    },
    {
      "num": 3,
      "name": "Heart 3",
      "description": "A heart shape with 3 dots",
      "dotLocations": [
        {"x": 270+83, "y": 80},
        {"x": 320+83, "y": 132},
        {"x": 270+83, "y": 194}
      ],
      "startAngle": 0,
      "endAngle": 0,
      "isClockwise": true
    },
    {
      "num": 4,
      "name": "Heart 4",
      "description": "Another heart shape with 3 dots",
      "dotLocations": [
        {"x": 270+83, "y": 80},
        {"x": 220+83, "y": 132},
        {"x": 270+83, "y": 194}
      ],
      "startAngle": 0,
      "endAngle": 0,
      "isClockwise": true
    },
    {
      "num": 5,
      "name": "Heart 5",
      "description": "A heart shape with 4 dots",
      "dotLocations": [
        {"x": 90+83, "y": 332},
        {"x": 162+83, "y": 332},
        {"x": 133+83, "y": 415},
        {"x": 90+83, "y": 446}
      ],
      "startAngle": 0,
      "endAngle": 0,
      "isClockwise": true
    },
    {
      "num": 6,
      "name": "Heart 6",
      "description": "Another heart shape with 4 dots",
      "dotLocations": [
        {"x": 90+83, "y": 332},
        {"x": 18+83, "y": 332},
        {"x": 47+83, "y": 415},
        {"x": 90+83, "y": 446}
      ],
      "startAngle": 0,
      "endAngle": 0,
      "isClockwise": true
    },
    {
      "num": 7,
      "name": "Heart 7",
      "description": "A heart shape with 4 dots",
      "dotLocations": [
        {"x": 270+83, "y": 332},
        {"x": 336+83, "y": 325},
        {"x": 316+83, "y": 397},
        {"x": 291+83, "y": 446}
      ],
      "startAngle": 0,
      "endAngle": 0,
      "isClockwise": true
    },
    {
      "num": 8,
      "name": "Heart 8",
      "description": "Another heart shape with 4 dots",
      "dotLocations": [
        {"x": 270+83, "y": 332},
        {"x": 207+83, "y": 353},
        {"x": 230+83, "y": 405},
        {"x": 291+83, "y": 446}
      ],
      "startAngle": 0,
      "endAngle": 0,
      "isClockwise": true
    }
  ]
}
